{
    "status":  "ok",
    "renderId":  "ra5jgqki",
    "renderMs":  599,
    "timings":  {
                    "sanitize":  0,
                    "loadJson":  2,
                    "mainIndex":  3,
                    "pages":  272,
                    "additional":  172,
                    "strip":  101,
                    "robots":  1,
                    "sitemap":  2,
                    "manifest":  0
                },
    "warnings":  [
                     {
                         "file":  "tr\\gizlilikpolitikasi\\style.css",
                         "placeholders":  [
                                              "--border_radius--",
                                              "--bgcolor--",
                                              "--card_shadow--",
                                              "--colortitle--",
                                              "--color--",
                                              "--coloractive--"
                                          ],
                         "brokenAttrs":  [

                                         ],
                         "badText":  [

                                     ]
                     },
                     {
                         "file":  "tr\\hakkimizda\\style.css",
                         "placeholders":  [
                                              "--border_radius--",
                                              "--bgcolor--",
                                              "--card_shadow--",
                                              "--colortitle--",
                                              "--color--",
                                              "--coloractive--"
                                          ],
                         "brokenAttrs":  [

                                         ],
                         "badText":  [

                                     ]
                     },
                     {
                         "file":  "tr\\kalitepolitikamiz\\style.css",
                         "placeholders":  [
                                              "--border_radius--",
                                              "--bgcolor--",
                                              "--card_shadow--",
                                              "--colortitle--",
                                              "--color--",
                                              "--coloractive--"
                                          ],
                         "brokenAttrs":  [

                                         ],
                         "badText":  [

                                     ]
                     },
                     {
                         "file":  "tr\\kariyer\\style.css",
                         "placeholders":  [
                                              "--border_radius--",
                                              "--bgcolor--",
                                              "--card_shadow--",
                                              "--colortitle--",
                                              "--color--",
                                              "--coloractive--"
                                          ],
                         "brokenAttrs":  [

                                         ],
                         "badText":  [

                                     ]
                     },
                     {
                         "file":  "tr\\kisiselveriler\\style.css",
                         "placeholders":  [
                                              "--border_radius--",
                                              "--bgcolor--",
                                              "--card_shadow--",
                                              "--colortitle--",
                                              "--color--",
                                              "--coloractive--"
                                          ],
                         "brokenAttrs":  [

                                         ],
                         "badText":  [

                                     ]
                     },
                     {
                         "file":  "tr\\kullanicahaklari\\style.css",
                         "placeholders":  [
                                              "--border_radius--",
                                              "--bgcolor--",
                                              "--card_shadow--",
                                              "--colortitle--",
                                              "--color--",
                                              "--coloractive--"
                                          ],
                         "brokenAttrs":  [

                                         ],
                         "badText":  [

                                     ]
                     },
                     {
                         "file":  "tr\\misyon\\style.css",
                         "placeholders":  [
                                              "--border_radius--",
                                              "--bgcolor--",
                                              "--card_shadow--",
                                              "--colortitle--",
                                              "--color--",
                                              "--coloractive--"
                                          ],
                         "brokenAttrs":  [

                                         ],
                         "badText":  [

                                     ]
                     },
                     {
                         "file":  "tr\\sss\\style.css",
                         "placeholders":  [
                                              "--border_radius--",
                                              "--bgcolor--",
                                              "--card_shadow--",
                                              "--colortitle--",
                                              "--color--",
                                              "--coloractive--"
                                          ],
                         "brokenAttrs":  [

                                         ],
                         "badText":  [

                                     ]
                     },
                     {
                         "file":  "tr\\style.css",
                         "placeholders":  [
                                              "--bgcolor--"
                                          ],
                         "brokenAttrs":  [

                                         ],
                         "badText":  [

                                     ]
                     },
                     {
                         "file":  "tr\\vizyon\\style.css",
                         "placeholders":  [
                                              "--border_radius--",
                                              "--bgcolor--",
                                              "--card_shadow--",
                                              "--colortitle--",
                                              "--color--",
                                              "--coloractive--"
                                          ],
                         "brokenAttrs":  [

                                         ],
                         "badText":  [

                                     ]
                     },
                     {
                         "file":  "tr\\yasaluyari\\style.css",
                         "placeholders":  [
                                              "--border_radius--",
                                              "--bgcolor--",
                                              "--card_shadow--",
                                              "--colortitle--",
                                              "--color--",
                                              "--coloractive--"
                                          ],
                         "brokenAttrs":  [

                                         ],
                         "badText":  [

                                     ]
                     }
                 ],
    "warningCount":  11,
    "issueCounts":  {
                        "placeholder":  61,
                        "brokenAttr":  0,
                        "badText":  0
                    }
}
